LICENSE
MANIFEST.in
README.rst
requirements.txt
run_toolbox.py
setup.cfg
setup.py
toolbox/__init__.py
toolbox/_common.py
toolbox/ansible_default_config.py
toolbox/benchmarking.py
toolbox/cluster.py
toolbox/codeflare.py
toolbox/entitlement.py
toolbox/from_config.py
toolbox/gpu_operator.py
toolbox/llm_load_test.py
toolbox/load_aware.py
toolbox/local_ci.py
toolbox/nfd.py
toolbox/nfd_operator.py
toolbox/notebooks.py
toolbox/ocm_addon.py
toolbox/pipelines.py
toolbox/repo.py
toolbox/rhods.py
toolbox/utils.py
toolbox/watsonx_serving.py
toolbox/wisdom.py
topsail.egg-info/PKG-INFO
topsail.egg-info/SOURCES.txt
topsail.egg-info/dependency_links.txt
topsail.egg-info/entry_points.txt
topsail.egg-info/requires.txt
topsail.egg-info/top_level.txt